{
  "nom": "Jennifer Lopez",
  "P373": "Jennifer Lopez",
  "P214": "42038339",
  "P213": [
    "0000000121299281",
    "0000000368640971",
    "000000036864098X"
  ],
  "P106": [
    "Q10800557",
    "Q3282637",
    "Q5716684",
    "Q2490358",
    "Q10798782"
  ],
  "P27": "Q30",
  "P19": "Q18426",
  "P434": "f0602f55-1770-483d-89bd-4bae0d0ac086",
  "P244": "no97019851",
  "P227": "122627121",
  "P345": "nm0000182",
  "P569": "+1969-07-24T00:00:00Z",
  "P358": "Q905349",
  "P31": "Q5",
  "P910": "Q8565477",
  "P646": "/m/043zg",
  "P268": "140175480",
  "P1273": "a10279660",
  "P735": [
    "Q4677161",
    "Q3841018"
  ],
  "P412": "Q186506",
  "P1006": "165956437",
  "P1284": "00000023552",
  "P1263": "033/000022964",
  "P937": "Q65",
  "P1971": "{'amount': '+2', 'unit': '1'}",
  "P1728": "mn0000317865",
  "P1953": "51984",
  "P2003": "jlo",
  "P2013": "jenniferlopez",
  "P1902": "2DlGxzQSjYe5N6G9nkYghR",
  "P26": [
    "Q26625",
    "Q744785",
    "Q24488369",
    "Q483118"
  ],
  "P1266": "12443",
  "P2019": "p144649",
  "P2002": "JLo",
  "P2435": "6990",
  "P2471": "jennifer-lopez",
  "P2163": "389551",
  "P2605": "564",
  "P2626": "106727",
  "P950": "XX1266889",
  "P2168": "217579",
  "P2604": "8766",
  "P2387": "244756",
  "P2519": "609",
  "P3222": "jennifer-lopez",
  "P136": [
    "Q851213",
    "Q45981",
    "Q37073",
    "Q18345375",
    "Q11401"
  ],
  "P264": [
    "Q216364",
    "Q193023",
    "Q190585",
    "Q3177666"
  ],
  "P3373": "Q925586",
  "P3430": "w6sf3rq3",
  "P3265": "jenniferlopez",
  "P3733": "318",
  "P3478": "95022",
  "P40": [
    "Q29109895",
    "Q40484771"
  ],
  "P2031": "+1986-00-00T00:00:00Z",
  "P3417": "Jennifer-Lopez-actor-musician",
  "P2984": "jlobts",
  "P2397": [
    "UCr8RjWUQ_9KYcIPmWiqBroQ",
    "UCx1f1u4XlFFr0YgqF3wB4lQ"
  ],
  "P3509": "jennifer-lopez",
  "P551": [
    "Q65",
    "Q60"
  ],
  "P3017": "jennifer-lopez",
  "P1258": "celebrity/jennifer_lopez",
  "P2688": "jenniferlopez",
  "P1559": "{'text': 'Jennifer Lopez', 'language': 'en'}",
  "P4332": "263",
  "P1015": "1095087",
  "P1207": "n02083915",
  "P3192": "Jennifer+Lopez",
  "P3040": "jenniferlopez",
  "P4985": "16866",
  "P1417": "biography/Jennifer-Lopez",
  "P1283": [
    "Q6178567",
    "Q6493409"
  ],
  "P109": "Jennifer Lopez Signature.svg",
  "P166": [
    "Q16889162",
    "Q56085709",
    "Q17985761",
    "Q604370",
    "Q5513594"
  ],
  "P2218": "{'amount': '+400000000', 'unit': 'http://www.wikidata.org/entity/Q4917'}",
  "P172": "Q7258666",
  "P734": [
    "Q26078995",
    "Q382833"
  ],
  "P269": "077446992",
  "P5534": "16866",
  "P1412": [
    "Q1860",
    "Q1321"
  ],
  "P1819": "I00583946",
  "P1315": "1457774",
  "P1296": "0263212",
  "P3569": "populaire-muziek/jennifer-lopez",
  "P4666": "1747",
  "P4657": "87600401",
  "P5882": "M00000106317",
  "P5287": "jennifer-lopez",
  "P5421": "102094",
  "P21": "Q6581072",
  "P691": "ola2002149985",
  "P6461": "jennifer-lopez",
  "P154": [
    "JenniferLopez.com blue logo.png",
    "JLove.png"
  ],
  "P1303": "Q17172850",
  "P6722": "31645",
  "P1477": "{'text': 'Jennifer Lynn Lopez', 'language': 'en'}",
  "P2722": "45",
  "P5905": [
    "4005-37487",
    "4040-114446"
  ],
  "P6874": "Jennifer-Lopez",
  "P7109": "jennifer_lopez",
  "P7214": "72015",
  "P2373": "Jennifer-lopez",
  "P6327": "66094",
  "P6517": "Jennifer-Lopez",
  "P6559": "7995",
  "P4342": "Jennifer_Lopez",
  "P6706": "Lòpez,+Jennifer+Lynn",
  "P6868": [
    "169518",
    "496078045"
  ],
  "P5240": "jennifer_lopez",
  "P4073": "jenniferlopez",
  "P1280": "9885283",
  "P1712": "person/jennifer-lopez",
  "P4515": "66053",
  "P3845": "156627",
  "P2638": "people/jennifer-lopez",
  "P4438": "4ce2bafe4c709",
  "P4326": "526913",
  "P6119": "jennifer-lopez",
  "P3136": "1982931",
  "P5284": "1019000",
  "P6446": "101777",
  "P3933": "1572144",
  "P3204": "102581",
  "P3056": "1163717",
  "P5340": "186539",
  "P3114": "4676",
  "P4682": "7106",
  "P5007": "Jennifer-Lopez",
  "P7215": "36687",
  "P4839": [
    "Entity[\"Person\", \"JenniferLopez::582pg\"]",
    "Entity[\"MusicAct\", \"JenniferLopez::zmhh6\"]"
  ],
  "P1343": "Q67311526",
  "P742": [
    "J.Lo",
    "J.LO",
    "J-Lo",
    "J-LO",
    "J Lo"
  ],
  "P3305": "48363",
  "P3142": "n0000444",
  "P4779": "3884",
  "P4782": "2017",
  "P4768": "73167",
  "P5254": "6795",
  "P3341": "829",
  "P6521": "52754",
  "P7300": "30867",
  "P5019": "lopez-jennifer",
  "P7704": "agent/base/146851",
  "P7803": "5526",
  "P856": "https://jenniferlopez.com",
  "P3388": "264104",
  "P1411": [
    "Q311836",
    "Q1011564",
    "Q7585305",
    "Q311836",
    "Q268200"
  ],
  "P4208": "jennifer-lopez",
  "P1580": "a1104686",
  "P8125": "410264",
  "P1741": "127315",
  "P7085": "jlo",
  "P2600": "6000000010073347173",
  "P5917": "463009",
  "P5404": "jennifer_lopez",
  "P1553": "145528",
  "P949": "002332280",
  "P7699": "LNB:cMd;=Bk",
  "P5034": "KAC2019E1461",
  "P1368": "000281421",
  "P409": "42364554",
  "P5431": "3bd6bc00",
  "P5145": "145",
  "P5033": "323",
  "P2850": "463009",
  "P4198": "Atb5lh6epirnh6higqudnit5zdq",
  "P7192": "m519441",
  "P7194": "l/lopez",
  "P6926": "jennifer-lopez",
  "P2581": "00855968n",
  "P6955": "Jennifer Lopez",
  "P6909": "Jennifer-Lopez",
  "P6983": "Jennifer Lopez",
  "P6839": "Music/JenniferLopez",
  "P4862": "B000API7VY",
  "P6276": "B000RW2N1U",
  "P6972": "jennifer-lopez",
  "P4576": "661",
  "P7156": "797",
  "P5154": [
    "qjit-edTX8Ds5Ol0F02JA08J",
    "0oPI6MAqAZvsMKdnXS"
  ],
  "P7210": "JENNIFER-LOPEZ,999914964",
  "P7151": "jennifer-lopez",
  "P7641": "v9gwcj/jennifer-lopez",
  "P6943": "jennifer-lopez",
  "P2909": "566",
  "P6351": "2487",
  "P5927": "jennifer_lopez_5713",
  "P7275": "749",
  "P7071": "jennifer-lopez",
  "P7050": "7186",
  "P6911": "Jennifer Lopez",
  "P7191": "13693",
  "P4473": "2845",
  "P5292": "jennifer-lopez",
  "P7157": "890",
  "P2963": "82052",
  "P7212": "jennifer-lopez-lyrics.html",
  "P5312": "3164",
  "P7483": "jennifer-lopez",
  "P6464": "913793",
  "P2190": "jenniferlopez",
  "P7808": "52574",
  "P7920": "277831",
  "P8349": "2614",
  "P3365": "jennifer-lynn-lopez",
  "P3984": "JenniferLopez",
  "P5337": "CAAqIQgKIhtDQkFTRGdvSUwyMHZNRFF6ZW1jU0FtUmxLQUFQAQ",
  "P5233": "a6262",
  "P7277": "ARzxcV9JrdchJzZ",
  "P7159": "1051731",
  "P7400": "lopezjennifer",
  "P3145": "nm178",
  "P7553": "28020",
  "P8305": "jennifer-lopez",
  "P8314": "100321",
  "P7653": "83948",
  "P648": "OL2741776A",
  "P1617": "40840de2-8c47-43d8-9f8e-78caf106423b",
  "P7195": "25900",
  "P5356": "Jennifer-Lopez",
  "P7119": "6459",
  "P8381": "jennifer-lopez",
  "P7303": "jennifer-lopez/14846",
  "P7865": "95a5yja38danyna29xb5yd1t60u32cg",
  "P7070": "Jennifer-Lopez",
  "P6262": [
    "es.mujeres:Jennifer_Lopez",
    "disney:Jennifer_Lopez"
  ],
  "P5184": "33XXXXX31487",
  "P998": [
    "Arts/People/L/Lopez,_Jennifer/",
    "World/Français/Arts/Arts_du_spectacle/Acteurs_et_actrices/L/Lopez,_Jennifer/",
    "World/Español/Artes/Artes_escénicas/Actuación/Actrices_y_actores/L/López,_Jennifer/",
    "World/Russian/Искусство/Музыка/Стили/Поп/Группы_и_исполнители/Lopez,_Jennifer/"
  ],
  "P4747": "mi00000000001db220",
  "P7188": "jennifer-lopez",
  "P7193": "12132",
  "P8313": "Jennifer_Lopez",
  "P3553": "20222472",
  "P7745": "44947",
  "P6922": "jennifer-lopez",
  "P1185": "145329",
  "P4193": "Jennifer_Lynn_Lopez_(1969)",
  "P7284": "jennifer-lopez",
  "P2572": "JenniferLopez",
  "P5327": "jennifer-lopez/filmografie",
  "P2087": "jennifer-lopez-f3a5",
  "P8041": "5030362",
  "P6960": "jennifer-lopez",
  "P7836": "542545",
  "P3812": "Jennifer-Lopez",
  "P8334": "131928",
  "P5361": "LopezJennifer1970-",
  "P7184": "043zg",
  "P8637": "7441",
  "P8819": "10663-jennifer-lopez",
  "P7189": "27156",
  "P7052": "035ada79-c000-44e0-b38d-edf2800e1de9",
  "P2942": "jenniferlopez",
  "P8013": "people/jennifer-lopez",
  "P7293": "9810542976105606",
  "P8895": "Jennifer_Lopez",
  "P8796": "40771",
  "P7923": "jennifer-lopez",
  "P7200": "453",
  "P8687": [
    "{'amount': '+100267114', 'unit': '1'}",
    "{'amount': '+45244388', 'unit': '1'}",
    "{'amount': '+190000000', 'unit': '1'}",
    "{'amount': '+140000000', 'unit': '1'}",
    "{'amount': '+110000000', 'unit': '1'}"
  ],
  "P8971": "71374",
  "P6081": "1017195502",
  "P8977": [
    "273491",
    "628095"
  ],
  "P8879": "182",
  "P9102": "437-jennifer-lopez",
  "P7201": "200204488481860608",
  "P8037": "160",
  "P8415": "123578",
  "P8672": "834935473512468480",
  "P9305": "P000001290",
  "P18": "Jennifer Lopez Interview 2019 (cropped).jpg",
  "P9316": "1377",
  "P9328": "20000268022",
  "P9322": "p0083991-Lopez-Jennifer-1970",
  "P6255": "15083",
  "P5617": "jennifer-lopez-12532",
  "P3368": "3757662",
  "P9404": "1287",
  "P9463": "16866",
  "P9469": "performers/Jennifer-Lopez",
  "P7502": "Jennifer_Lopez",
  "P6882": "Jennifer Lopez",
  "P8189": "987007447972405171",
  "P7217": "jennifer-lopez",
  "P6894": "208769",
  "P8179": "ncf10469692",
  "P1005": "1642504",
  "P3065": "02-A005815013",
  "P6965": "Jennifer Lopez",
  "P7672": "jennifer lopez",
  "P6964": "jennifer lopez",
  "P6896": "amVubmlmZXIgbG9wZXo",
  "P7196": "236",
  "P7354": "714748",
  "P7190": "90",
  "P7198": "Jennifer-Lopez",
  "P6970": "Jennifer Lopez",
  "P6914": "jennifer-lopez",
  "P6918": "Jennifer_Lopez",
  "P6968": "Jennifer_Lopez",
  "P7187": "Jennifer Lopez",
  "P7205": "jennifer-lopez",
  "P7206": "TlRFMA",
  "P1889": [
    "Q6178557",
    "Q88845059",
    "Q105720913"
  ],
  "P9662": "132766",
  "P451": [
    "Q558664",
    "Q216936",
    "Q33240",
    "Q483118",
    "Q26625"
  ],
  "P3479": "71ed270a486c2977b8c12b15b4627cc4dc389bab",
  "P9694": "jenniferlopez",
  "P8309": "18-148845",
  "P9775": "jennifer-lopez",
  "P6200": "cqnvjndq916t",
  "P1828": "00352848639",
  "P6275": "Q891885",
  "P1151": "Q6493548",
  "P9864": "132",
  "P1424": "Q6493693",
  "P9743": "107aDoFRsi",
  "P7185": "jennifer-lopez,tg-Vm15-aJwU-xwQa",
  "P4204": "Jennifer-Lopez",
  "P9937": "60",
  "P25": "Q108840907",
  "P7522": "0038441",
  "P9965": "3775",
  "P9995": "4236",
  "P9984": "981058517164606706",
  "P1695": "a0000001254900",
  "P10052": "jennifer_lopez",
  "P10097": "dzhennifer-lopes",
  "P6739": "2093",
  "P10180": "14936584",
  "P10163": "182",
  "P10166": "jennifer-lopez",
  "P10194": "nm161219",
  "P10234": "jennifer_lopez",
  "P10266": "12443",
  "P10268": "112",
  "P10288": "jennifer_lopez",
  "P1649": "00049985",
  "P3846": "87097919124649",
  "P10297": "m043zg",
  "P10415": "2502",
  "P6621": "jennifer-lopez",
  "P8591": "A2262724",
  "P10608": "agent/gnd_122627121",
  "P10621": "1000181",
  "P10660": "71430",
  "P6923": "00023228",
  "P6927": "jennifer-lopez",
  "P10372": "4895",
  "P10757": "8620",
  "P10302": "dzhennifer-lopes",
  "P103": [
    "Q1860",
    "Q1321"
  ],
  "P10820": "447658",
  "P4970": [
    "JLo",
    "Jennifer Affleck"
  ],
  "P10900": "1064",
  "P10895": "Jennifer-Lopez",
  "P10909": "jennifer-lopez",
  "P10916": "Jennifer_Lopez",
  "P10885": "1686",
  "P10524": "257009",
  "P10445": "60932",
  "P10410": "004D2wTq0agSKi",
  "P11047": "122884038849215",
  "P10305": "djennifer-lopes",
  "P7815": "jennifer-lopez",
  "P6634": "thejlo",
  "P11090": "1845029",
  "P6967": "Jennifer_Lopez",
  "P7353": "27352",
  "P6912": "jennifer-lopez",
  "P11168": "pqbEldj-SKU_",
  "P11194": "people/jennifer-lopez",
  "P11237": "10062629",
  "P8969": "15949",
  "P10699": "jennifer-lopez",
  "P11345": "jennifer-lopez-sv866o28",
  "P8419": "Jennifer \"JLO\" Lopez",
  "P11407": "240903",
  "P11386": "jennifer-lopez",
  "P11454": "288896",
  "P11434": "64427",
  "P11449": "31913",
  "P9917": "art/cinema/actor/lopez",
  "P11646": "O3K-yFuBZ",
  "P11686": "981058517164606706",
  "P11683": "jennifer-lopez-3496",
  "P3836": "jlo",
  "P2639": "7240072631df4d35afcb2597d9143d45",
  "P22": "Q108840906",
  "P11800": "360",
  "P11892": "jlo",
  "P11819": "20000050",
  "P1830": "Q121433776",
  "P10780": "jennifer-lopez",
  "P12098": "20320",
  "P8136": "jennifer-lopez",
  "P10540": "lopes-dzhennifer",
  "P12153": "306842260",
  "P12152": "jennifer-lopez",
  "P12140": "jennifer-lopez",
  "P8092": "Jennifer_López",
  "P8885": "제니퍼 로페즈",
  "P4167": "Jennifer_Lopez",
  "P12126": "Jennifer_Lopez",
  "P12309": "hm7Otsvu9ShbXwq2PnHSI",
  "P12320": "jennifer-lopez",
  "P12349": "jennifer-lopez",
  "P8445": "97071",
  "P11245": "JenniferLopez",
  "P12385": "jennifer-lopez",
  "P2949": "Lopez-5633",
  "P12582": "20110803100114673",
  "P10832": "E39PBJdM9TJrJGD6YYpGkPW7HC",
  "P12800": "fr:Jennifer_Lopez",
  "P12836": "27224724",
  "P12854": "5d77682aa091de001f2e6781",
  "P12627": "jennifer_lopez"
}