{
  "nom": "Kamala Harris",
  "P373": "Kamala Harris",
  "P214": "91053810",
  "P21": "Q6581072",
  "P102": "Q29552",
  "P31": "Q5",
  "P569": "+1964-10-20T00:00:00Z",
  "P106": [
    "Q82955",
    "Q40348",
    "Q600751",
    "Q36180"
  ],
  "P27": "Q30",
  "P244": "n2009045056",
  "P735": [
    "Q20898922",
    "Q668902"
  ],
  "P2267": "kamala-harris",
  "P2002": [
    "KamalaHarris",
    "VP",
    "SenKamalaHarris"
  ],
  "P646": "/m/08sry2",
  "P172": [
    "Q39086965",
    "Q49085",
    "Q6127409",
    "Q7681242",
    "Q2643509"
  ],
  "P345": "nm3668431",
  "P2390": "Kamala_Harris",
  "P2013": [
    "KamalaHarris",
    "VicePresident",
    "SenatorKamalaHarris"
  ],
  "P2003": [
    "kamalaharris",
    "vp"
  ],
  "P1157": "H001075",
  "P3344": "120012",
  "P1839": [
    "S6CA00584",
    "P00009423"
  ],
  "P3430": "w6q534xz",
  "P2686": "N00036915",
  "P551": [
    "Q65",
    "Q62",
    "Q61",
    "Q340",
    "Q7984463"
  ],
  "P463": [
    "Q3308284",
    "Q2015366"
  ],
  "P1263": "824/000163335",
  "P1559": "{'text': 'Kamala Harris', 'language': 'en'}",
  "P3373": "Q16729668",
  "P2397": [
    "UCe1ciA1TDa5F9K6Ufr_6Fsw",
    "UC0XBsJpPhOLg0k4x9ZwrWzw"
  ],
  "P213": "0000000065826859",
  "P734": "Q10859343",
  "P1329": "+1-202-224-3553",
  "P1412": [
    "Q1860",
    "Q7976",
    "Q8002"
  ],
  "P937": [
    "Q62",
    "Q18013",
    "Q61"
  ],
  "P2190": "kamalaharris",
  "P109": "Kamala Harris Signature.svg",
  "P910": "Q65626184",
  "P6886": "Q7976",
  "P5008": "Q15304953",
  "P2949": "Harris-37912",
  "P227": "1181140676",
  "P18": [
    "Kamala Harris Vice Presidential Portrait.jpg",
    "Kamala Harris official photo.jpg"
  ],
  "P1417": "biography/Kamala-Harris",
  "P25": "Q60844968",
  "P22": "Q60894135",
  "P3602": [
    "Q22923830",
    "Q18356713",
    "Q15964770",
    "Q5020249",
    "Q101110072"
  ],
  "P26": "Q65029113",
  "P1038": [
    "Q16196331",
    "Q96224414",
    "Q98382417",
    "Q98382515",
    "Q102055307"
  ],
  "P2600": "6000000010726328284",
  "P3846": "87097946202457",
  "P7293": "9810608296105606",
  "P2581": "02472797n",
  "P5337": "CAAqIggKIhxDQkFTRHdvSkwyMHZNRGh6Y25reUVnSmxiaWdBUAE",
  "P4839": "Entity[\"Person\", \"KamalaHarris::8d5w3\"]",
  "P3417": "Kamala-Harris-politician",
  "P5361": "HarrisKamala1964-",
  "P2963": "3143641",
  "P648": [
    "OL7448059A",
    "OL6717038A"
  ],
  "P7400": "harriskamala",
  "P2019": "p899690",
  "P5233": "a568448",
  "P5033": "2753592",
  "P2604": "2311031",
  "P6119": "kamala-harris",
  "P6464": "2378465",
  "P7920": "488509",
  "P4985": "2065569",
  "P3845": "248757",
  "P5254": "332551",
  "P4515": "24724165",
  "P1712": "person/kamala-harris",
  "P1258": "celebrity/kamala_harris",
  "P7284": "kamala-harris",
  "P2087": "kamala-d-harris",
  "P3899": "KamalaHarris",
  "P3017": "kamala-harris",
  "P1617": "9bff5537-f5e4-401c-93a2-b0ca484bb131",
  "P5551": "kamala-harris",
  "P4167": "Kamala_Harris",
  "P3509": "kamala-harris",
  "P5184": "33XXX1491613",
  "P998": [
    "Regional/North_America/United_States/California/Government/Federal/US_Senate/Kamala_Harris_[D]/",
    "Society/History/By_Region/North_America/United_States/Vice_Presidents/Harris,_Kamala/"
  ],
  "P4013": "kamalaharris",
  "P3106": "us-news/kamala-harris",
  "P2850": "423079475",
  "P3192": "Kamala+Harris",
  "P6621": "kamala-harris",
  "P3388": "92446",
  "P3222": "kamala-harris",
  "P6654": "KamalaHarris",
  "P6328": "4318",
  "P7775": "Kamala_Harris",
  "P5264": "kamala-d-harris-4719450",
  "P3984": "KamalaHarris",
  "P5421": "145492",
  "P3365": "kamala-devi-harris",
  "P3553": "20681644",
  "P6760": "28268",
  "P5404": "kamala-harris",
  "P2984": "kamalaharris",
  "P4342": "Kamala_Harris",
  "P6868": "2256145810",
  "P3479": "27849c38-1e10-4dac-8004-9e7f66793558",
  "P793": [
    "Q65059839",
    "Q127688121"
  ],
  "P1477": [
    "{'text': 'Kamala Devi Harris', 'language': 'en'}",
    "{'text': 'Kamala Iyer Harris', 'language': 'en'}"
  ],
  "P451": "Q5365075",
  "P8313": "Kamala_Harris",
  "P800": [
    "Q60717044",
    "Q102036019",
    "Q102079066"
  ],
  "P4862": "B002KMPG0K",
  "P6200": "c34k011x7rrt",
  "P8094": "harriskamal",
  "P1284": "00000032149",
  "P7929": "p=kamala;n=harris",
  "P1482": "https://politics.stackexchange.com/tags/kamala-harris",
  "P6723": "african-american-history/harris-kamala-devi-1964",
  "P53": "Q98476216",
  "P103": [
    "Q7976",
    "Q1860"
  ],
  "P1472": "Kamala Harris",
  "P6553": "L484",
  "P101": [
    "Q117488",
    "Q64812306",
    "Q7163",
    "Q7748"
  ],
  "P552": "Q3039938",
  "P166": [
    "Q56255521",
    "Q63072219",
    "Q101422305",
    "Q604370"
  ],
  "P2048": [
    "{'amount': '+1.57', 'unit': 'http://www.wikidata.org/entity/Q11573'}",
    "{'amount': '+64.25', 'unit': 'http://www.wikidata.org/entity/Q218593'}"
  ],
  "P935": "Kamala Harris",
  "P19": [
    "Q7074025",
    "Q17042"
  ],
  "P69": [
    "Q3577853",
    "Q1068752",
    "Q7989327",
    "Q3077363"
  ],
  "P512": [
    "Q1540185",
    "Q1765120"
  ],
  "P8568": "views-on-israel-of-u-s-presidential-candidates-2020-kamala-harris",
  "P108": [
    "Q7413997",
    "Q7413997",
    "Q5020429"
  ],
  "P1015": "1593520724092",
  "P8687": [
    "{'amount': '+4634861', 'unit': '1'}",
    "{'amount': '+3597098', 'unit': '1'}",
    "{'amount': '+10800000', 'unit': '1'}",
    "{'amount': '+19377885', 'unit': '1'}"
  ],
  "P8309": "18-298715",
  "P6839": "UsefulNotes/KamalaHarris",
  "P269": "25104145X",
  "P1971": "{'amount': '+0', 'unit': '1'}",
  "P4527": "477221",
  "P2924": "5991893",
  "P9368": "kamala-harris",
  "P7666": "kamala-harris",
  "P1280": "397235971",
  "P7502": "Kamala_Harris",
  "P3368": "3779005",
  "P3812": "Kamala-Harris",
  "P9743": "107ZztJE6I",
  "P6573": "Kamala_Harris",
  "P4104": "125849",
  "P691": "xx0266382",
  "P8189": "987009511885005171",
  "P10632": "Q10853588",
  "P1050": "Q84263196",
  "P8693": "Q100250021",
  "P10660": "1018696",
  "P10757": "11539",
  "P11194": "people/kamala-harris",
  "P11615": "person/kamala-harris",
  "P140": "Q93191",
  "P9984": "981059738156806706",
  "P268": "17941872t",
  "P8179": "ncf13685274",
  "P7699": "LNB:DFRj;=Bc",
  "P349": "031517062",
  "P271": "DA19731103",
  "P7029": "770241779",
  "P1006": "43041692X",
  "P1207": "n2021143446",
  "P3065": "02-A029023944",
  "P10832": "E39PBJcc9JyDBhJKwqhccjQg8C",
  "P4012": "71860612",
  "P11496": "1140851849822988047",
  "P10780": "kamala-harris",
  "P8445": "19376",
  "P39": [
    "Q57596296",
    "Q85222257",
    "Q3406489",
    "Q4416090",
    "Q4416090"
  ],
  "P12086": "Kamala_Harris",
  "P9802": "2193928",
  "P5034": "KAC202398402",
  "P11386": "kamala-harris",
  "P2919": "Kamala Harris in SignWriting.svg",
  "P742": [
    "賀錦麗",
    "Hạ Cẩm Lệ",
    "Hạ Cẩm Ly"
  ],
  "P990": "Kamala Harris speaks on the Americans with Disabilities Act.ogg",
  "P856": [
    "https://www.whitehouse.gov/administration/vice-president-harris/",
    "https://kamalaharris.com/"
  ],
  "P10457": "kamala-harris",
  "P12644": "412678",
  "P4666": "2095895",
  "P4204": "kamala-harris",
  "P11500": "15032442523",
  "P3267": [
    "158848119@N08",
    "153763616@N06"
  ],
  "P12800": [
    "en:Kamala_Harris",
    "it:Kamala_Harris",
    "es:Kamala_Harris",
    "eu:Kamala_Harris",
    "fr:Kamala_Harris"
  ],
  "P3390": "SEK-ar14212604",
  "P11892": "kamalaharris",
  "P7085": "kamalaharris",
  "P973": "https://www.whitehouse.gov/administration/vice-president-harris/",
  "P1449": "{'text': 'Momala', 'language': 'en'}",
  "P12153": "241768263",
  "P396": "UBOV026227",
  "P5797": "kamalaharris",
  "P8462": "harris6.html#165.81.40",
  "P13049": "1181140676",
  "P434": "dd51245e-528b-4829-9bf2-7df9ec8d01be"
}