{
  "nom": "Lady Gaga",
  "P735": [
    "Q18607242",
    "Q14968419",
    "Q1097621"
  ],
  "P19": "Q6523170",
  "P138": "Q605031",
  "P358": "Q568635",
  "P373": "Lady Gaga",
  "P106": [
    "Q177220",
    "Q753110",
    "Q5716684",
    "Q10800557",
    "Q488205"
  ],
  "P27": "Q30",
  "P434": "650e7db6-b795-4eb5-a702-5ea2fc46c848",
  "P244": "no2008179258",
  "P214": "49555103",
  "P213": "0000000120254559",
  "P227": "135898838",
  "P345": "nm3078932",
  "P737": [
    "Q5383",
    "Q15862",
    "Q1744",
    "Q689823",
    "Q2831"
  ],
  "P910": "Q6540040",
  "P31": "Q5",
  "P856": "https://ladygaga.com",
  "P569": [
    "+1986-03-28T00:00:00Z",
    "+1986-03-20T00:00:00Z"
  ],
  "P646": "/m/0478__m",
  "P268": "157535900",
  "P1151": "Q6539895",
  "P1273": "a11042485",
  "P172": [
    "Q974693",
    "Q857880"
  ],
  "P551": [
    "Q429687",
    "Q7338894",
    "Q65",
    "Q128114",
    "Q11299"
  ],
  "P69": [
    "Q796480",
    "Q861418",
    "Q797078",
    "Q1542213",
    "Q5059890"
  ],
  "P1303": [
    "Q5994",
    "Q1112687",
    "Q31561",
    "Q78987",
    "Q163829"
  ],
  "P451": [
    "Q98026080",
    "Q554315",
    "Q98026074"
  ],
  "P1344": [
    "Q889643",
    "Q3300629",
    "Q3632246",
    "Q13979",
    "Q406497"
  ],
  "P166": [
    "Q595693",
    "Q917698",
    "Q372123",
    "Q935283",
    "Q2976730"
  ],
  "P793": [
    "Q13563471",
    "Q428476",
    "Q473206",
    "Q72758",
    "Q600236"
  ],
  "P1343": [
    "Q17290934",
    "Q67311526"
  ],
  "P349": "01204423",
  "P691": "xx0099107",
  "P409": "47753387",
  "P906": "344910",
  "P1015": "9060029",
  "P950": "XX5078972",
  "P269": "162075545",
  "P1006": "322038480",
  "P412": "Q186506",
  "P1286": "02000001637",
  "P136": [
    "Q188450",
    "Q211756",
    "Q1298934",
    "Q851213",
    "Q25094849"
  ],
  "P742": "Lady Gaga",
  "P1263": "339/000206718",
  "P1728": "mn0000994823",
  "P1953": [
    "1103159",
    "1525683"
  ],
  "P2003": "ladygaga",
  "P2002": "ladygaga",
  "P1902": "1HY2Jd0NmPuamShAr6KMms",
  "P1412": [
    "Q1860",
    "Q150",
    "Q188"
  ],
  "P1258": "celebrity/lady_gaga",
  "P1477": "{'text': 'Stefani Joanne Angelina Germanotta', 'language': 'en'}",
  "P1266": "417702",
  "P2019": "p669908",
  "P2168": "457328",
  "P2163": "1785765",
  "P2013": "ladygaga",
  "P2387": "1506973",
  "P2435": "324588",
  "P2519": "63420",
  "P2605": "56805",
  "P264": [
    "Q21091",
    "Q654283",
    "Q231694",
    "Q946523",
    "Q38903"
  ],
  "P1424": "Q6539132",
  "P3192": "Lady+Gaga",
  "P3106": "music/lady-gaga",
  "P2847": [
    "+LadyGaga",
    "106063255260898090789"
  ],
  "P1553": "1438",
  "P2604": "1669323",
  "P2722": "75491",
  "P3417": "Lady-Gaga-musician",
  "P2850": "277293880",
  "P2471": "lady-gaga",
  "P3569": "populaire-muziek/lady-gaga",
  "P3478": "974908",
  "P1559": "{'text': 'Lady Gaga', 'language': 'en'}",
  "P2031": "+2005-00-00T00:00:00Z",
  "P3265": "ladygaga",
  "P2984": "ladygaga",
  "P2949": "Germanotta-1",
  "P3017": "lady-gaga",
  "P1050": "Q540571",
  "P4208": "lady-gaga",
  "P396": "UBOV304849",
  "P1315": "1479624",
  "P2373": "Lady-gaga",
  "P4198": "Ah7amohgkrydyfxgsbask752lye",
  "P3040": "ladygaga",
  "P734": "Q42865121",
  "P1472": "Lady Gaga",
  "P4104": "86714",
  "P101": [
    "Q37073",
    "Q12752882",
    "Q222749"
  ],
  "P1280": "159794531",
  "P109": "Lady Gaga autograph.svg",
  "P1449": [
    "{'text': 'Mother Monster', 'language': 'en'}",
    "{'text': 'Gaga', 'language': 'en'}",
    "{'text': 'New Queen of Pop', 'language': 'en'}"
  ],
  "P4985": "237405",
  "P1741": "213954",
  "P5587": "gdsw2r702b7zvvq",
  "P1417": "biography/Lady-Gaga",
  "P4839": [
    "Entity[\"Person\", \"LadyGaga::c33v4\"]",
    "Entity[\"MusicAct\", \"LadyGaga::38b48\"]"
  ],
  "P5291": "lady-gaga",
  "P21": "Q6581072",
  "P18": "Lady Gaga at Joe Biden's inauguration (cropped 5).jpg",
  "P6461": "lady-gaga",
  "P2354": [
    "Q25037020",
    "Q741348"
  ],
  "P5292": "lady-gaga",
  "P443": "Lady Gaga ready for upload.ogg",
  "P6722": "31681",
  "P102": "Q29552",
  "P6760": "8701",
  "P5905": [
    "4005-68720",
    "4040-118110"
  ],
  "P6960": "lady-gaga",
  "P1828": [
    "00519338344",
    "00519338442"
  ],
  "P6275": "Q891885",
  "P3222": "lady-gaga",
  "P4073": [
    "ladygaga",
    "es.gaga",
    "fr.ladygaga",
    "ru.ladygaga",
    "es.gagapedia"
  ],
  "P3509": "lady-gaga",
  "P4013": "ladygaga",
  "P1296": "0519485",
  "P4666": "176760",
  "P4657": "417840401",
  "P5882": "M00000321714",
  "P6150": "2035",
  "P6517": "Lady-Gaga",
  "P6559": "5334",
  "P6327": "113837",
  "P4342": "Lady_Gaga",
  "P6868": "402911475",
  "P949": "001717028",
  "P7105": "lady-gaga",
  "P7109": "lady_gaga",
  "P7157": "471",
  "P7212": "lady-gaga-lyrics.html",
  "P3056": "11392985",
  "P1712": "person/lady-gaga",
  "P5033": "1147113",
  "P5534": "236400",
  "P4515": "8929380",
  "P4332": "33209",
  "P3845": "294098",
  "P2638": "people/lady-gaga",
  "P4438": "4ce2bdda07379",
  "P4326": "1323598",
  "P6119": "lady-gaga",
  "P7214": "873875",
  "P3136": "2005032",
  "P5284": "1269788",
  "P6446": "102117",
  "P5340": "349004",
  "P3933": "9580531",
  "P3204": "348376",
  "P3114": "89208",
  "P4682": "106005",
  "P5007": "Lady-Gaga",
  "P5421": "219849",
  "P7215": "86954",
  "P7195": "22741",
  "P989": "EN-Lady Gaga-article.ogg",
  "P7317": "39335",
  "P5034": "KAC201714300",
  "P3388": "67011",
  "P5019": "lady-gaga",
  "P3305": "302523",
  "P3142": "n0021515",
  "P4779": "146909",
  "P4782": "226716",
  "P4768": "312820",
  "P5254": "105682",
  "P3341": "29650",
  "P6521": "381242",
  "P7300": "47896",
  "P7578": "lady-gaga",
  "P552": "Q789447",
  "P7192": "Lady-Gaga-m526945",
  "P8041": "10370550",
  "P8125": "375816",
  "P91": "Q43200",
  "P6058": [
    "personnage/Stefani_Joanne_Angelina_Germanotta_dite_Lady_Gaga/185825",
    "images/Lady_Gaga/1313108",
    "images/Lady_Gaga/1313109"
  ],
  "P7085": "ladygaga",
  "P1283": "Q16457917",
  "P1207": "n2010304041",
  "P4619": "000489148",
  "P7369": "000801962",
  "P8179": "ncf12142632",
  "P3846": "87097919140105",
  "P8189": "987007520766005171",
  "P7699": "LNB:CCkU;=Bc",
  "P1368": "000156538",
  "P271": "DA17587141",
  "P1375": "000550508",
  "P7293": "9810616312005606",
  "P3065": "02-A016386685",
  "P7039": "000083719",
  "P1695": "a0000002489816",
  "P1890": "000844007",
  "P6262": [
    "es.mujeres:Lady_Gaga",
    "ladygaga:Lady_Gaga",
    "es.gaga:Lady_Gaga",
    "disney:Lady_Gaga",
    "youtube:Lady_Gaga"
  ],
  "P5154": [
    "DcmCyi0xuwYZJl80F07zT08J",
    "TaEBocy6ixtKeBjCo_"
  ],
  "P3839": "1336",
  "P4576": "3534754",
  "P5145": "80046429",
  "P5287": "lady-gaga",
  "P5356": "Lady-Gaga",
  "P5404": "lady-gaga",
  "P5431": "1bd665bc",
  "P5917": "277293880",
  "P5927": "lady_gaga_21818",
  "P6276": "B0016SK9OW",
  "P6874": "Lady-Gaga",
  "P6882": "Lady Gaga",
  "P6894": "140979",
  "P6896": "TGFkeSBHYWdh",
  "P7354": "1249444",
  "P7200": "137438984319",
  "P7763": "Q73555012",
  "P8301": "56473",
  "P8672": "806227321669591040",
  "P7929": "p=stefani;n=germanotta",
  "P8094": "germanottas",
  "P25": "Q64011269",
  "P3373": "Q70473487",
  "P22": "Q100925287",
  "P3812": "Lady-Gaga",
  "P3553": "19558854",
  "P2397": [
    "UCNL1ZadSjHpjm4q9j2sVtOA",
    "UC07Kxew-cMIaykMOkzqHtBQ"
  ],
  "P8819": "27895-lady-gaga",
  "P7803": "87951",
  "P1411": [
    "Q1027880",
    "Q1027891",
    "Q112243",
    "Q112243",
    "Q103618"
  ],
  "P3913": "453040",
  "P6839": "Music/LadyGaga",
  "P8895": "Lady_Gaga",
  "P7194": "l/ladygaga",
  "P6449": "136358",
  "P5361": "LadyGaga",
  "P3984": "LadyGaga",
  "P7184": "0478__m",
  "P8980": "000190556",
  "P6955": "Lady Gaga",
  "P8687": [
    "{'amount': '+83216805', 'unit': '1'}",
    "{'amount': '+20100000', 'unit': '1', 'upperBound': '+20199999', 'lowerBound': '+20100000'}",
    "{'amount': '+84098857', 'unit': '1'}",
    "{'amount': '+20000000', 'unit': '1'}",
    "{'amount': '+84906261', 'unit': '1'}"
  ],
  "P140": "Q5043",
  "P8977": "622749",
  "P8879": "1834371",
  "P6200": "cwz4l58yeg9t",
  "P7201": "200346971627324820",
  "P9172": "15304",
  "P8415": "153225",
  "P3847": "person:lady_gaga",
  "P9305": "P000104292",
  "P9328": "30069538864",
  "P9322": "0274922-Lady-Gaga-1986",
  "P9316": "15530",
  "P8037": "205332",
  "P7553": "245961",
  "P6683": "277168",
  "P6844": "165137",
  "P6255": "111758",
  "P5617": "lady-gaga-41310",
  "P7666": "lady-gaga",
  "P9404": "37066",
  "P103": "Q1860",
  "P9463": "237405",
  "P9469": "performers/Lady-Gaga",
  "P7502": "Lady_Gaga",
  "P7483": "lady-gaga",
  "P7303": "lady-gaga/3611",
  "P7672": "lady gaga",
  "P6964": "lady gaga",
  "P6965": "Lady Gaga",
  "P7196": "26905",
  "P7190": "6972",
  "P7198": "Lady-Gaga",
  "P2600": "6000000007723253626",
  "P648": "OL7317992A",
  "P6970": "Lady Gaga",
  "P6914": "lady-gaga",
  "P6918": "Lady_GaGa",
  "P6968": "Lady_GaGa",
  "P7187": "Lady Gaga",
  "P7205": "lady-gaga",
  "P7206": "TlRNeE9USXo",
  "P6900": "lady gaga",
  "P9662": "258153",
  "P7050": "686",
  "P2963": "2945649",
  "P3479": "9b9aa88a104cf4b794a0aefeede3b7d96235f846",
  "P9694": "ladygaga",
  "P8309": "18-133004",
  "P3365": "lady-gaga",
  "P4223": "lady-gaga",
  "P9775": "lady-gaga",
  "P2909": "43820",
  "P6920": "Lady+Gaga",
  "P9864": "112990",
  "P9743": "107a4Yqtee",
  "P6132": "lady-gaga",
  "P7185": "lady-gaga,tg-ApWR-xXUg-BbVM",
  "P4204": "Lady-Gaga",
  "P9937": "33546",
  "P9965": "144909",
  "P9995": "198475",
  "P9984": "981058518938906706",
  "P10052": "lady_gaga_",
  "P10097": "ledi-gaga",
  "P10166": "lady-gaga",
  "P8313": "Lady_Gaga",
  "P10288": "lady_gaga",
  "P8419": "Lady Gaga",
  "P10415": "17361",
  "P7052": "a661a9bb-ace6-4fb3-9e86-8e6612ab40e0",
  "P10410": "001D3C3T2wxP74",
  "P2626": "260791",
  "P2190": "stefanigermanotta",
  "P6621": "lady-gaga",
  "P10553": "572485603",
  "P10297": "m0478__m",
  "P8591": "A2242033",
  "P10660": "9265524",
  "P6923": "00075210",
  "P6927": "lady-gaga",
  "P10757": "1045",
  "P3828": "Q938131",
  "P10820": "500343",
  "P7653": "13921",
  "P10900": "4696641",
  "P10895": "Lady-Gaga",
  "P10524": "188170",
  "P10445": "64147",
  "P10266": "417702",
  "P3502": "ladygaga-blog",
  "P11047": "122882856780400",
  "P8381": "lady-gaga",
  "P7815": "lady-gaga",
  "P11090": "1927236",
  "P10291": "41747",
  "P10699": "lady-gaga",
  "P7353": "13695",
  "P6967": "Lady_Gaga",
  "P10180": "61282342",
  "P6912": "lady-gaga",
  "P10780": "lady-gaga",
  "P11168": "XVoOcEoDG84_",
  "P11194": "people/lady-gaga",
  "P8969": "82598",
  "P11237": "20166682",
  "P1649": "00168477",
  "P7808": "374631",
  "P5312": "5700",
  "P10268": "21143",
  "P10163": "1891772",
  "P10621": "305749",
  "P7923": "lady-gaga",
  "P7193": "1938934",
  "P7151": "lady-gaga",
  "P8013": "people/lady-gaga",
  "P7920": "321349",
  "P7284": "lady-gaga",
  "P6983": "Lady Gaga",
  "P7191": "290167",
  "P10916": "Lady_Gaga",
  "P6950": "lady-gaga",
  "P6081": "244244341",
  "P7071": "lady-gaga",
  "P7277": "ARgqzfvflptzxrX",
  "P10194": "nm383198",
  "P10372": "91071",
  "P6926": "lady-gaga",
  "P7275": "110335",
  "P7506": "937657",
  "P6972": "lady-gaga",
  "P7070": [
    "Lady-Gaga",
    "Stefani-Germanotta"
  ],
  "P8334": "145282",
  "P1284": "00000032737",
  "P7745": "284268",
  "P7189": [
    "13336",
    "310505"
  ],
  "P6922": "lady-gaga",
  "P4473": "253688",
  "P8305": "lady-gaga-1",
  "P7188": "lady-gaga",
  "P4747": "mi00000000001647e1",
  "P7400": "gagalady",
  "P8637": "85328",
  "P6943": "lady-gaga",
  "P3145": "nm89497",
  "P7156": "1425",
  "P7210": "LADY-GAGA,9999280533",
  "P5337": "CAAqJAgKIh5DQkFTRUFvS0wyMHZNRFEzT0Y5ZmJSSUNaR1VvQUFQAQ",
  "P6351": "447",
  "P5233": "a216657",
  "P10302": "ledi-gaga",
  "P5327": "lady-gaga/filmografie",
  "P10234": "lady_gaga",
  "P11345": "lady-gaga-r5bpic8x",
  "P5184": "33XXXX252187",
  "P6706": "Lady+Gaga",
  "P2942": "ladygaga",
  "P998": "Arts/Music/Bands_and_Artists/L/Lady_Gaga/",
  "P2087": "lady-gaga",
  "P8851": "75070729",
  "P9102": "37842-lady-gaga",
  "P6909": "Lady-GaGa",
  "P1617": "18595906-9159-437c-b7a2-419ac671e0ee",
  "P2581": "01018189n",
  "P10885": "8620917",
  "P7119": "120784",
  "P11386": "lady-gaga",
  "P11454": "371988",
  "P11434": "238759",
  "P11449": "70231",
  "P11196": "ladygaga",
  "P9917": "art/music/pop/lady_gaga",
  "P11487": "ladygaga",
  "P11496": "1140282266679923584",
  "P11646": "4aoPyFOBb",
  "P11683": "ledi-gaga",
  "P11686": "981058518938906706",
  "P11800": "362",
  "P11933": "19",
  "P1830": "Q122200546",
  "P10540": "ledi-gaga",
  "P12098": "963104",
  "P3544": "62891",
  "P8092": "Lady_Gaga",
  "P8885": "레이디 가가",
  "P12086": "Lady_Gaga",
  "P12385": "lady-gaga",
  "P6394": [
    "12404494",
    "12404482"
  ],
  "P9171": "3211",
  "P1005": "1854346",
  "P12153": "592348496",
  "P12800": [
    "es:Lady_Gaga",
    "fr:Lady_Gaga"
  ],
  "P12836": "27475785",
  "P12979": "lady-gaga",
  "P108": [
    "Q231694",
    "Q333040",
    "Q21091",
    "Q889363",
    "Q1175790"
  ],
  "P800": [
    "Q861409",
    "Q191070",
    "Q131182",
    "Q189007",
    "Q153029"
  ],
  "P8693": "Q16657517"
}