{
  "nom": "Nicki Minaj",
  "P358": "Q1508969",
  "P434": "1036b808-f58c-4a3e-b461-a2c4492ecf1b",
  "P373": "Nicki Minaj",
  "P244": "no2010042410",
  "P227": "142847925",
  "P345": "nm3747326",
  "P21": "Q6581072",
  "P910": "Q9041227",
  "P31": "Q5",
  "P569": "+1982-12-08T00:00:00Z",
  "P19": "Q7401398",
  "P27": "Q754",
  "P646": "/m/047sxrj",
  "P1286": "02000001758",
  "P136": [
    "Q11401",
    "Q37073",
    "Q2572585",
    "Q850412",
    "Q211756"
  ],
  "P1263": "388/000269578",
  "P1953": [
    "1615988",
    "1729326"
  ],
  "P1728": [
    "mn0001013175",
    "mn0002428706"
  ],
  "P2002": "NICKIMINAJ",
  "P2003": "nickiminaj",
  "P1902": "0hCNtLu0JehylgoiP8L4Gh",
  "P1266": "535668",
  "P2019": "p535634",
  "P172": [
    "Q49085",
    "Q6025447"
  ],
  "P264": [
    "Q1047366",
    "Q4413456",
    "Q1070152"
  ],
  "P69": "Q3072747",
  "P2013": "nickiminaj",
  "P1411": [
    "Q595693",
    "Q4835473",
    "Q4809486",
    "Q7564366",
    "Q1091031"
  ],
  "P166": [
    "Q4835473",
    "Q16974858",
    "Q17106719",
    "Q19858088",
    "Q263702"
  ],
  "P2373": [
    "Nicki-minaj",
    "Nicki-minaj-and-lil-wayne",
    "Nicki-minaj-drake-and-lil-wayne",
    "William-and-nicki-minaj",
    "A-ap-rocky-a-ap-ferg-and-nicki-minaj"
  ],
  "P2168": "445347",
  "P2435": "486504",
  "P2604": "2324615",
  "P2605": "72882",
  "P2519": "66156",
  "P2949": "Maraj-1",
  "P3192": [
    "Niki+Minaj",
    "Nicki+Minaj"
  ],
  "P3106": "music/nicki-minaj",
  "P154": "Nicki Minaj logo.svg",
  "P2638": "people/nicki-minaj",
  "P1258": [
    "celebrity/nicky_minaj",
    "celebrity/nicki_minaj"
  ],
  "P3265": "nickiminaj",
  "P3478": "1435335",
  "P3417": "Nicki-Minaj-musician",
  "P3017": "nicki-minaj",
  "P1477": "{'text': 'Onika Tanya Maraj', 'language': 'en'}",
  "P2984": "nickiminaj",
  "P1417": "biography/Nicki-Minaj",
  "P4208": "nicki-minaj",
  "P1015": "15004373",
  "P2850": "278464538",
  "P4198": "Al2hj7qbgbxxezdzrlxgvety6he",
  "P2847": "118345505161219385606",
  "P101": "Q11895763",
  "P2397": [
    "UC3jOd7GUMhpgJRBhiLzuLsg",
    "UCTTcTeAszDGxALRSMkJH9FQ"
  ],
  "P213": "0000000122969945",
  "P1741": "263046",
  "P1412": "Q1860",
  "P268": "16215529v",
  "P269": "157332810",
  "P2031": "+2004-00-00T00:00:00Z",
  "P735": [
    "Q96148199",
    "Q2288133"
  ],
  "P734": [
    "Q36995343",
    "Q12669358"
  ],
  "P5917": "40748725",
  "P4657": "258350401",
  "P1280": "187771235",
  "P2163": "1787295",
  "P4666": "442256",
  "P4839": "Entity[\"MusicAct\", \"NickiMinaj::pmxw2\"]",
  "P5882": "M00000339191",
  "P4073": [
    "nickiminaj",
    "es.nickiminaj"
  ],
  "P1830": "Q55437507",
  "P6351": "92",
  "P1303": "Q17172850",
  "P6461": "nicki-minaj",
  "P6517": "Nicki-Minaj",
  "P6578": "36B93B304B9D0660",
  "P6760": "8700",
  "P5905": [
    "4005-93281",
    "4040-114517"
  ],
  "P6874": "nicky-minaj",
  "P7109": "nicki_minaj",
  "P691": "xx0138378",
  "P451": [
    "Q20744680",
    "Q1897911"
  ],
  "P2688": "nickiminaj",
  "P5240": "nicki_minaj",
  "P214": "76145970087732250928",
  "P6868": "475624852",
  "P6559": "6414",
  "P6327": "979966",
  "P1559": "{'text': 'Onika Maraj', 'language': 'en'}",
  "P7704": "agent/base/114763",
  "P2471": "nicki-minaj",
  "P949": "004872715",
  "P3065": "02-A021540268",
  "P4342": "Nicki_Minaj",
  "P1424": "Q10891339",
  "P6262": "taylorswift:Nicki_Minaj",
  "P7085": "nickiminaj",
  "P4576": "3702744",
  "P4013": "nickiminaj",
  "P2722": "382937",
  "P7192": "Nicki-Minaj-m497738",
  "P463": "Q99493768",
  "P1971": "{'amount': '+1', 'unit': '1'}",
  "P6255": "193925",
  "P856": "http://www.nickiminajofficial.com/",
  "P7194": "n/nickiminaj",
  "P8687": [
    "{'amount': '+22109896', 'unit': '1'}",
    "{'amount': '+21800000', 'unit': '1'}",
    "{'amount': '+130298921', 'unit': '1'}",
    "{'amount': '+48492860', 'unit': '1'}",
    "{'amount': '+168000000', 'unit': '1'}"
  ],
  "P8672": "806590795469836288",
  "P9328": "30334493714",
  "P9463": "968660",
  "P9404": "60276",
  "P3040": "nickiminaj",
  "P3373": "Q106678927",
  "P8041": "10432054",
  "P6972": "nicki-minaj",
  "P7303": "nicki-minaj/4579",
  "P3984": "Nicki_Minaj",
  "P4985": "968660",
  "P9694": "nickiminaj",
  "P8309": "18-148186",
  "P7212": "nicki-minaj-lyrics.html",
  "P5404": "nicki_minaj",
  "P2909": "47525",
  "P6960": "nicki-minaj",
  "P9937": "117939",
  "P4204": "Nicki-Minaj",
  "P9864": "192985",
  "P5007": "Nicki-Minaj",
  "P8189": "987007361264505171",
  "P10097": "niki-minazh",
  "P10166": "nicki-minaj",
  "P9995": "245658",
  "P3368": "722323",
  "P7052": "f7b95089-ca7f-45b5-8535-3c4a9a0ae3af",
  "P3114": "90812",
  "P2600": "6000000015772116056",
  "P742": "Nicki Minaj",
  "P18": "Nicki Minaj Vogue 2024 02.jpg",
  "P7201": "200026611867826432",
  "P11047": "122882856202979",
  "P8125": "457741",
  "P6276": "B0017PUOJ4",
  "P3846": "87097991579855",
  "P7699": "LNB:C9f/;=BT",
  "P4514": "32997",
  "P11194": "people/nicki-minaj",
  "P1283": "Q17102147",
  "P10302": "nicki-minaj",
  "P5292": "nicki-minaj",
  "P11683": "niki_minazh",
  "P106": [
    "Q2252262",
    "Q177220",
    "Q753110",
    "Q10800557",
    "Q33999"
  ],
  "P1828": "00477174720",
  "P6275": "Q7120528",
  "P460": "Q55417838",
  "P1617": "43153075-c5e5-4d35-b4ab-5299ecfec57f",
  "P6200": "c34w7pvy363t",
  "P11819": "30174455",
  "P10780": "nicki-minaj",
  "P26": "Q71948883",
  "P10832": "E39PBJhhp9xGfQqhqH34mjMHG3",
  "P5356": "Nicki-Minaj",
  "P10": "Nicki Minaj Performs “Majesty,” “Barbie Dreams,” “Ganja Burn,” “FeFe” - MTV VMAs - Live Performance.webm",
  "P6914": [
    "nicki-minaj",
    "onika-maraj"
  ],
  "P12098": "1205453",
  "P7084": [
    "Q4121328",
    "Q8768843",
    "Q8679090",
    "Q9303438",
    "Q9571195"
  ],
  "P6104": "Q122691297",
  "P2354": [
    "Q21051259",
    "Q6592203",
    "Q56276708",
    "Q3254220"
  ],
  "P12086": "Nicki_Minaj",
  "P11245": "NickiMinajAtVEVO",
  "P11386": "nicki-minaj",
  "P12800": "fr:Nicki_Minaj",
  "P3579": "2127483195",
  "P10445": "70183"
}